sopel_py/__init__.py
sopel_py-1.0.1.dist-info/COPYING
sopel_py-1.0.1.dist-info/METADATA
sopel_py-1.0.1.dist-info/WHEEL
sopel_py-1.0.1.dist-info/entry_points.txt
sopel_py-1.0.1.dist-info/top_level.txt
sopel_py-1.0.1.dist-info/RECORD
