Metadata-Version: 2.1
Name: sopel-py
Version: 1.0.1
Summary: Sopel Python Eval Plugin
Home-page: https://github.com/sopel-irc/sopel-py
Author: dgw
Author-email: dgw@technobabbl.es
License: Eiffel Forum License, version 2
Platform: UNKNOWN
Classifier: Intended Audience :: Developers
Classifier: Intended Audience :: System Administrators
Classifier: License :: Eiffel Forum License (EFL)
Classifier: License :: OSI Approved :: Eiffel Forum License
Classifier: Topic :: Communications :: Chat :: Internet Relay Chat
Requires-Python: >=3.7
Requires-Dist: sopel (<9,>=7.1)
